pytest_ethereum/__init__.py
pytest_ethereum/deployer.py
pytest_ethereum/exceptions.py
pytest_ethereum/linker.py
pytest_ethereum/plugins.py
pytest_ethereum/typing.py
pytest_ethereum/utils/__init__.py
pytest_ethereum/utils/linker.py
pytest_ethereum-0.1.2.dist-info/METADATA
pytest_ethereum-0.1.2.dist-info/RECORD
pytest_ethereum-0.1.2.dist-info/WHEEL
pytest_ethereum-0.1.2.dist-info/entry_points.txt
pytest_ethereum-0.1.2.dist-info/top_level.txt
